mercadolivresdk/__init__.py
mercadolivresdk/product_manager.py
mercadolivresdk/product_model.py
mercadolivreverifications/__init__.py
mercadolivreverifications/product_manager.py
mercadolivreverifications/product_model.py
mercadolivreverifications/products_verifications.py
mercadolivreverifications-0.0.1.dist-info/LICENSE
mercadolivreverifications-0.0.1.dist-info/METADATA
mercadolivreverifications-0.0.1.dist-info/WHEEL
mercadolivreverifications-0.0.1.dist-info/top_level.txt
mercadolivreverifications-0.0.1.dist-info/RECORD
