Metadata-Version: 2.1
Name: mercadolivreverifications
Version: 0.0.1
Summary: biblioteca para facilitar investigações no mercado livre
Home-page: https://github.com/Luc45-Pereira/mercadolivreverifications
Author: Lucas Pereira de Lima
Author-email: lucaspereiradelima94@gmail.com
Classifier: Programming Language :: Python :: 3
Classifier: License :: OSI Approved :: MIT License
Classifier: Operating System :: OS Independent
Requires-Python: >=3.6
License-File: LICENSE
Requires-Dist: requests
Requires-Dist: pydantic
Requires-Dist: asyncio
